nnsp/__init__.py
nnsp-0.1.0.dist-info/LICENSE
nnsp-0.1.0.dist-info/METADATA
nnsp-0.1.0.dist-info/WHEEL
nnsp-0.1.0.dist-info/top_level.txt
nnsp-0.1.0.dist-info/RECORD
